RabbitSpider/__init__.py
RabbitSpider/default_settings.py
RabbitSpider/rabbit_go.py
RabbitSpider/core/__init__.py
RabbitSpider/core/download.py
RabbitSpider/core/engine.py
RabbitSpider/core/scheduler.py
RabbitSpider/dupefilters/__init__.py
RabbitSpider/dupefilters/redisdupefilter.py
RabbitSpider/dupefilters/setdupefilter.py
RabbitSpider/http/__init__.py
RabbitSpider/http/request.py
RabbitSpider/http/response.py
RabbitSpider/items/__init__.py
RabbitSpider/items/item.py
RabbitSpider/middlewares/__init__.py
RabbitSpider/middlewares/retry.py
RabbitSpider/pipelines/__init__.py
RabbitSpider/templates/project/__init__.py
RabbitSpider/templates/project/items.tmpl
RabbitSpider/templates/project/middlewares.tmpl
RabbitSpider/templates/project/pipelines.tmpl
RabbitSpider/templates/project/settings.tmpl
RabbitSpider/templates/project/spiders/__init__.py
RabbitSpider/templates/project/spiders/basic.tmpl
RabbitSpider/utils/__init__.py
RabbitSpider/utils/control.py
RabbitSpider/utils/exceptions.py
RabbitSpider/utils/log.py
RabbitSpider/utils/template.py
RabbitSpider-2.4.dist-info/METADATA
RabbitSpider-2.4.dist-info/WHEEL
RabbitSpider-2.4.dist-info/entry_points.txt
RabbitSpider-2.4.dist-info/top_level.txt
RabbitSpider-2.4.dist-info/RECORD
