Metadata-Version: 2.1
Name: RabbitSpider
Version: 2.4
Home-page: https://github.com/YunTom/RabbitSpider/tree/master
Author: 一纸
Author-email: 2395396520@qq.com
Requires-Python: >=3.8
Requires-Dist: aio-pika >=9.4.1
Requires-Dist: curl-cffi >=0.6.2
Requires-Dist: loguru >=0.7.2
Requires-Dist: parsel >=1.9.1
Requires-Dist: pydantic >=2.7.0
Requires-Dist: redis >=5.0.3
Requires-Dist: w3lib >=2.1.2
Requires-Dist: chardet >=5.2.0
